su.aes-0.1.6-py3.7-nspkg.pth
su/aes.py
su.aes-0.1.6.dist-info/LICENSE
su.aes-0.1.6.dist-info/METADATA
su.aes-0.1.6.dist-info/WHEEL
su.aes-0.1.6.dist-info/entry_points.txt
su.aes-0.1.6.dist-info/namespace_packages.txt
su.aes-0.1.6.dist-info/top_level.txt
su.aes-0.1.6.dist-info/RECORD
