Metadata-Version: 2.1
Name: su.aes
Version: 0.1.6
Summary: A simple encrypt/decrypt lib based on AES.
Home-page: https://github.com/zhaolins/su.aes
Author: Zhaolin Su
Author-email: z@suho.me
License: MIT
Keywords: development
Platform: UNKNOWN
Classifier: Development Status :: 4 - Beta
Classifier: Intended Audience :: Developers
Classifier: Topic :: Software Development :: Libraries
Classifier: License :: OSI Approved :: MIT License
Classifier: Programming Language :: Python :: 3.6
Requires-Dist: pycrypto
